{
    "accuracy": 100,
    "damage_class": "physical",
    "description_en": "Steals 1/2 of the damage inflicted.",
    "description_fr": "Une attaque qui aspire le sang de l’ennemi. La moitié des dégâts sont convertis en PV pour le lanceur.",
    "effect_chance": null,
    "effect_changes": [],
    "effect_entries": null,
    "id": 141,
    "meta": {
        "ailment_name": "none",
        "ailment_chance": 0,
        "category_name": "damage-heal",
        "crit_rate": 0,
        "drain": 50,
        "flinch_chance": 0,
        "healing": 0,
        "max_hits": null,
        "max_turns": null,
        "min_hits": null,
        "min_turns": null,
        "stat_chance": 0
    },
    "shortname": "leech-life",
    "name_fr": "Vampirisme",
    "name_en": "Leech Life",
    "power": 80,
    "pp": 10,
    "priority": 0,
    "stat_changes": [],
    "target_name": "selected-pokemon",
    "type_name": "bug"
}