{
    "accuracy": null,
    "damage_class": "status",
    "description_en": "The user draws attention to itself, making all targets take aim only at the user.",
    "effect_chance": null,
    "effect_changes": [],
    "effect_entries": null,
    "id": 266,
    "meta": {
        "ailment_name": "none",
        "ailment_chance": 0,
        "category_name": "unique",
        "crit_rate": 0,
        "drain": 0,
        "flinch_chance": 0,
        "healing": 0,
        "max_hits": null,
        "max_turns": null,
        "min_hits": null,
        "min_turns": null,
        "stat_chance": 0
    },
    "shortname": "follow-me",
    "name_fr": "Par Ici",
    "name_en": "Follow Me",
    "power": null,
    "pp": 20,
    "priority": 2,
    "stat_changes": [],
    "target_name": "user",
    "type_name": "normal"
}