{
    "accuracy": 90,
    "damage_class": "physical",
    "description_en": "Hurls boulders at the foe 2 to 5 times in a row.",
    "effect_chance": null,
    "effect_changes": [],
    "effect_entries": null,
    "id": 350,
    "meta": {
        "ailment_name": "none",
        "ailment_chance": 0,
        "category_name": "damage",
        "crit_rate": 0,
        "drain": 0,
        "flinch_chance": 0,
        "healing": 0,
        "max_hits": 5,
        "max_turns": null,
        "min_hits": 2,
        "min_turns": null,
        "stat_chance": 0
    },
    "shortname": "rock-blast",
    "name_fr": "Boule Roc",
    "name_en": "Rock Blast",
    "power": 25,
    "pp": 10,
    "priority": 0,
    "stat_changes": [],
    "target_name": "selected-pokemon",
    "type_name": "rock"
}