{
    "accuracy": 100,
    "damage_class": "special",
    "description_en": "Has a chance to confuse the target.",
    "description_fr": "A une chance de rendre la cible confuse.",
    "effect_chance": 20,
    "effect_changes": [],
    "effect_entries": null,
    "id": 352,
    "meta": {
        "ailment_name": "confusion",
        "ailment_chance": 20,
        "category_name": "damage-ailment",
        "crit_rate": 0,
        "drain": 0,
        "flinch_chance": 0,
        "healing": 0,
        "max_hits": null,
        "max_turns": 5,
        "min_hits": null,
        "min_turns": 2,
        "stat_chance": 0
    },
    "shortname": "water-pulse",
    "name_fr": "Vibraqua",
    "name_en": "Water Pulse",
    "power": 60,
    "pp": 20,
    "priority": 0,
    "stat_changes": [],
    "target_name": "selected-pokemon",
    "type_name": "water"
}