{
    "accuracy": null,
    "damage_class": "status",
    "description_en": "The user breaks its shell, lowering its Defense and Sp. Def stats but sharply raising Attack, Sp. Atk, and Speed stats.",
    "description_fr": "Le lanceur brise sa coquille. Il baisse sa Défense et Déf. Spé., mais augmente forte- ment son Attaque, Atq. Spé. et Vitesse.",
    "effect_chance": null,
    "effect_changes": [],
    "effect_entries": null,
    "id": 504,
    "meta": {
        "ailment_name": "none",
        "ailment_chance": 0,
        "category_name": "unique",
        "crit_rate": 0,
        "drain": 0,
        "flinch_chance": 0,
        "healing": 0,
        "max_hits": null,
        "max_turns": null,
        "min_hits": null,
        "min_turns": null,
        "stat_chance": 0
    },
    "shortname": "shell-smash",
    "name_fr": "Exuviation",
    "name_en": "Shell Smash",
    "power": null,
    "pp": 15,
    "priority": 0,
    "stat_changes": [
        {
            "change": -1,
            "stat": {
                "name": "defense",
                "url": "https://pokeapi.co/api/v2/stat/3/"
            }
        },
        {
            "change": -1,
            "stat": {
                "name": "special-defense",
                "url": "https://pokeapi.co/api/v2/stat/5/"
            }
        },
        {
            "change": 2,
            "stat": {
                "name": "attack",
                "url": "https://pokeapi.co/api/v2/stat/2/"
            }
        },
        {
            "change": 2,
            "stat": {
                "name": "special-attack",
                "url": "https://pokeapi.co/api/v2/stat/4/"
            }
        },
        {
            "change": 2,
            "stat": {
                "name": "speed",
                "url": "https://pokeapi.co/api/v2/stat/6/"
            }
        }
    ],
    "target_name": "user",
    "type_name": "normal"
}