{
    "accuracy": 90,
    "damage_class": "physical",
    "description_en": "The user swings its stone axes at the target, aiming to land a critical hit. Stone splinters left behind by this attack continue to damage the target for several turns.",
    "description_fr": "Le lanceur attaque le point faible de sa cible avec sa hache de pierre. Les débris de pierre continuent d'infliger des dégâts à la cible plusieurs fois.",
    "effect_chance": null,
    "effect_changes": [],
    "effect_entries": null,
    "id": 830,
    "meta": {
        "ailment_name": null,
        "ailment_chance": null,
        "category_name": null,
        "crit_rate": null,
        "drain": null,
        "flinch_chance": null,
        "healing": null,
        "max_hits": null,
        "max_turns": null,
        "min_hits": null,
        "min_turns": null,
        "stat_chance": null
    },
    "shortname": "stone-axe",
    "name_fr": "Hache de Pierre",
    "name_en": "Stone Axe",
    "power": 65,
    "pp": 15,
    "priority": 0,
    "stat_changes": [],
    "target_name": "selected-pokemon",
    "type_name": "rock"
}