{
    "id": 358,
    "name": "chimecho",
    "form": "chimecho-mega",
    "abilities": [
        {
            "ability": {
                "name": "levitate",
                "url": "https://pokeapi.co/api/v2/ability/26/"
            },
            "is_hidden": false,
            "slot": 1
        }
    ],
    "stats": [
        {
            "base_stat": 75,
            "effort": 0,
            "stat": {
                "name": "hp",
                "url": "https://pokeapi.co/api/v2/stat/1/"
            }
        },
        {
            "base_stat": 50,
            "effort": 0,
            "stat": {
                "name": "attack",
                "url": "https://pokeapi.co/api/v2/stat/2/"
            }
        },
        {
            "base_stat": 110,
            "effort": 0,
            "stat": {
                "name": "defense",
                "url": "https://pokeapi.co/api/v2/stat/3/"
            }
        },
        {
            "base_stat": 135,
            "effort": 0,
            "stat": {
                "name": "special-attack",
                "url": "https://pokeapi.co/api/v2/stat/4/"
            }
        },
        {
            "base_stat": 120,
            "effort": 0,
            "stat": {
                "name": "special-defense",
                "url": "https://pokeapi.co/api/v2/stat/5/"
            }
        },
        {
            "base_stat": 65,
            "effort": 0,
            "stat": {
                "name": "speed",
                "url": "https://pokeapi.co/api/v2/stat/6/"
            }
        }
    ],
    "types": [
        {
            "slot": 1,
            "type": {
                "name": "psychic",
                "url": "https://pokeapi.co/api/v2/type/14/"
            }
        },
        {
            "slot": 2,
            "type": {
                "name": "steel",
                "url": "https://pokeapi.co/api/v2/type/9/"
            }
        }
    ],
    "weight": 80,
    "moves": [
        "35",
        "38",
        "50",
        "86",
        "94",
        "95",
        "103",
        "105",
        "113",
        "115",
        "120",
        "156",
        "164",
        "173",
        "174",
        "182",
        "196",
        "203",
        "204",
        "214",
        "215",
        "219",
        "226",
        "227",
        "240",
        "241",
        "244",
        "247",
        "248",
        "253",
        "263",
        "269",
        "270",
        "271",
        "273",
        "278",
        "281",
        "282",
        "285",
        "286",
        "304",
        "313",
        "319",
        "322",
        "326",
        "347",
        "356",
        "361",
        "412",
        "428",
        "430",
        "433",
        "447",
        "451",
        "473",
        "496",
        "500",
        "502",
        "505",
        "555",
        "577",
        "586",
        "605",
        "797",
        "917"
    ]
}